chconsole/__init__.py
chconsole/__main__.py
chconsole/_version.py
chconsole/connect/__init__.py
chconsole/connect/curie.py
chconsole/connect/remote_connector.py
chconsole/entry/__init__.py
chconsole/entry/chat_area.py
chconsole/entry/chat_area_filter.py
chconsole/entry/code_area.py
chconsole/entry/code_area_filter.py
chconsole/entry/entry.py
chconsole/entry/history.py
chconsole/entry/history_filter.py
chconsole/entry/line_prompt.py
chconsole/entry/line_prompt_filter.py
chconsole/entry/named_stacked_layout.py
chconsole/launch/__init__.py
chconsole/launch/gui_main.py
chconsole/launch/join.py
chconsole/launch/launch.py
chconsole/launch/launch_config.py
chconsole/launch/launch_widget.py
chconsole/launch/shell_main.py
chconsole/main/__init__.py
chconsole/main/chat_console_app.py
chconsole/main/expanded_main_window.py
chconsole/main/launch_app.py
chconsole/main/main_window.py
chconsole/main/push_button.py
chconsole/main/statusbar.py
chconsole/main/toggle_button.py
chconsole/main/resources/icon/JupyterConsole.svg
chconsole/media/__init__.py
chconsole/media/image.py
chconsole/media/line_iter.py
chconsole/media/right_aligned.py
chconsole/media/text.py
chconsole/media/text_register.py
chconsole/menus/__init__.py
chconsole/menus/image_context_menu.py
chconsole/menus/text_context_menu.py
chconsole/messages/__init__.py
chconsole/messages/export_item.py
chconsole/messages/import_item.py
chconsole/messages/kernel_message.py
chconsole/messages/meta_command.py
chconsole/messages/source.py
chconsole/pager/__init__.py
chconsole/pager/pager.py
chconsole/pager/pager_filter.py
chconsole/receiver/__init__.py
chconsole/receiver/outbuffer.py
chconsole/receiver/receiver.py
chconsole/receiver/receiver_filter.py
chconsole/run_kernel/__init__.py
chconsole/run_kernel/chc_python.py
chconsole/run_kernel/run_remote.py
chconsole/standards/__init__.py
chconsole/standards/base_event_filter.py
chconsole/standards/document_config.py
chconsole-0.1.22.dist-info/DESCRIPTION.rst
chconsole-0.1.22.dist-info/METADATA
chconsole-0.1.22.dist-info/RECORD
chconsole-0.1.22.dist-info/WHEEL
chconsole-0.1.22.dist-info/entry_points.txt
chconsole-0.1.22.dist-info/metadata.json
chconsole-0.1.22.dist-info/top_level.txt
