Metadata-Version: 2.0
Name: chconsole
Version: 0.1.22
Summary: Jupyter/Qt-based Chat Console
Home-page: https://github.com/mincode/chconsole
Author: Manfred Minimair
Author-email: chconsole@gmail.com
License: BSD
Keywords: Interactive,Interpreter,Shell
Platform: Linux
Platform: Mac OS X
Platform: Windows
Classifier: Intended Audience :: Developers
Classifier: Intended Audience :: System Administrators
Classifier: Intended Audience :: Science/Research
Classifier: License :: OSI Approved :: BSD License
Classifier: Programming Language :: Python
Classifier: Programming Language :: Python :: 3
Classifier: Programming Language :: Python :: 3.3
Requires-Dist: traitlets
Requires-Dist: jupyter-core
Requires-Dist: jupyter-client (>=4.1)
Requires-Dist: qtconsole (>=4.1pygments)
Requires-Dist: paramiko
Requires-Dist: requests
Requires-Dist: psycopg2
Requires-Dist: ipykernel (>=4.1)
Provides-Extra: doc
Requires-Dist: Sphinx (>=1.3); extra == 'doc'
Provides-Extra: test
Requires-Dist: mock; python_version=="2.7" and extra == 'test'
Provides-Extra: test
Requires-Dist: pexpect; sys_platform != "win32" and extra == 'test'
